LICENSE
MANIFEST.in
README.MD
setup.py
metropy/__init__.py
metropy/__main__.py
metropy.egg-info/PKG-INFO
metropy.egg-info/SOURCES.txt
metropy.egg-info/dependency_links.txt
metropy.egg-info/entry_points.txt
metropy.egg-info/requires.txt
metropy.egg-info/top_level.txt
metropy/sounds/__init__.py
metropy/sounds/bar.wav
metropy/sounds/beat.wav