Metadata-Version: 2.1
Name: metropy
Version: 0.5
Summary: Metronome with Terminal UI in ncurses
Home-page: https://github.com/Docheinstein/metropy
Author: Stefano Dottore
Author-email: docheinstein@gmail.com
License: MIT
Keywords: metronome
Platform: UNKNOWN
Requires-Python: >=3.6
